Workbook

Sheet Instrucciones
A1: PLANTILLA DE PRESUPUESTO - EYM OFICINAS (v0.1, compatible con Odoo 14 Community)
A3: Celdas amarillas = datos que usted llena. El resto se calcula solo.
A4: 1. Proyecto: datos del cliente y porcentajes (AIU, IVA, vigencia).
A5: 2. Catalogo: productos y materiales. Use los mismos codigos que en Odoo (Referencia interna).
A6: 3. Presupuesto: una linea por item. Al elegir el codigo, trae descripcion, UdM y precio del Catalogo.
A7: 4. Resumen: totales por capitulo, AIU, IVA y total.
A8: 5. Cortes: lista de piezas de tablero/vidrio para optimizar cortes.
A9: 6. Import_Odoo: se genera desde Presupuesto; guardar como CSV (UTF-8) e importar en Ventas > Cotizaciones.
A11: Estado de precio en Catalogo: Confirmado (cotizacion proveedor), Referencia (precio publico/estimado), Pendiente.
A12: Los porcentajes y tarifas de impuestos son ejemplos editables: verifiquelos con su contador antes de emitir.

Sheet Proyecto
A1: Cliente
A2: NIT / Cedula
A3: Contacto
A4: Proyecto
A5: Direccion / Ciudad
A6: Fecha
A7: Vigencia de la oferta (dias) | B7: 15
A8: Administracion % | B8: 0.1
A9: Imprevistos % | B9: 0.03
A10: Utilidad % | B10: 0.07
A11: IVA % | B11: 0.19
A12: Aplicar AIU (IVA solo sobre utilidad)? (SI/NO) | B12: NO
A13: Anticipo % | B13: 0.5

Sheet Catalogo
A1: Codigo (ref. interna Odoo) | B1: Nombre | C1: Categoria | D1: UdM | E1: Costo | F1: Precio venta | G1: Proveedor | H1: Fecha precio | I1: Estado precio | J1: Notas
A2: TAB-MEL-15-BL | B2: Tablero melamina blanco 15mm 1.83x2.44 | C2: Tableros | D2: und | E2: 0 | F2: 0 | I2: Pendiente | J2: Lamina estandar 1830x2440
A3: TAB-MDF-15 | B3: Tablero MDF crudo 15mm 1.83x2.44 | C3: Tableros | D3: und | E3: 0 | F3: 0 | I3: Pendiente
A4: VID-TEM-8 | B4: Vidrio templado 8mm | C4: Vidrio | D4: m2 | E4: 0 | F4: 0 | I4: Pendiente
A5: DRY-DIV-2C | B5: División drywall doble cara | C5: Obra civil | D5: m2 | E5: 0 | F5: 0 | I5: Pendiente
A6: MO-INST | B6: Mano de obra instalacion | C6: Mano de obra | D6: dia | E6: 0 | F6: 0 | I6: Pendiente

Sheet Presupuesto
A1: Capitulo | B1: Codigo | C1: Descripcion | D1: UdM | E1: Cantidad | F1: Precio unitario | G1: Subtotal | H1: Observacion
C2: =IF(B2="","",IFERROR(VLOOKUP(B2,Catalogo!$A:$F,2,FALSE),"CODIGO NO ENCONTRADO")) | D2: =IF(B2="","",IFERROR(VLOOKUP(B2,Catalogo!$A:$F,4,FALSE),"")) | F2: =IF(B2="","",IFERROR(VLOOKUP(B2,Catalogo!$A:$F,6,FALSE),0)) | G2: =IF(B2="","",E2*F2)
C3: =IF(B3="","",IFERROR(VLOOKUP(B3,Catalogo!$A:$F,2,FALSE),"CODIGO NO ENCONTRADO")) | D3: =IF(B3="","",IFERROR(VLOOKUP(B3,Catalogo!$A:$F,4,FALSE),"")) | F3: =IF(B3="","",IFERROR(VLOOKUP(B3,Catalogo!$A:$F,6,FALSE),0)) | G3: =IF(B3="","",E3*F3)
C4: =IF(B4="","",IFERROR(VLOOKUP(B4,Catalogo!$A:$F,2,FALSE),"CODIGO NO ENCONTRADO")) | D4: =IF(B4="","",IFERROR(VLOOKUP(B4,Catalogo!$A:$F,4,FALSE),"")) | F4: =IF(B4="","",IFERROR(VLOOKUP(B4,Catalogo!$A:$F,6,FALSE),0)) | G4: =IF(B4="","",E4*F4)
C5: =IF(B5="","",IFERROR(VLOOKUP(B5,Catalogo!$A:$F,2,FALSE),"CODIGO NO ENCONTRADO")) | D5: =IF(B5="","",IFERROR(VLOOKUP(B5,Catalogo!$A:$F,4,FALSE),"")) | F5: =IF(B5="","",IFERROR(VLOOKUP(B5,Catalogo!$A:$F,6,FALSE),0)) | G5: =IF(B5="","",E5*F5)
C6: =IF(B6="","",IFERROR(VLOOKUP(B6,Catalogo!$A:$F,2,FALSE),"CODIGO NO ENCONTRADO")) | D6: =IF(B6="","",IFERROR(VLOOKUP(B6,Catalogo!$A:$F,4,FALSE),"")) | F6: =IF(B6="","",IFERROR(VLOOKUP(B6,Catalogo!$A:$F,6,FALSE),0)) | G6: =IF(B6="","",E6*F6)
C7: =IF(B7="","",IFERROR(VLOOKUP(B7,Catalogo!$A:$F,2,FALSE),"CODIGO NO ENCONTRADO")) | D7: =IF(B7="","",IFERROR(VLOOKUP(B7,Catalogo!$A:$F,4,FALSE),"")) | F7: =IF(B7="","",IFERROR(VLOOKUP(B7,Catalogo!$A:$F,6,FALSE),0)) | G7: =IF(B7="","",E7*F7)
C8: =IF(B8="","",IFERROR(VLOOKUP(B8,Catalogo!$A:$F,2,FALSE),"CODIGO NO ENCONTRADO")) | D8: =IF(B8="","",IFERROR(VLOOKUP(B8,Catalogo!$A:$F,4,FALSE),"")) | F8: =IF(B8="","",IFERROR(VLOOKUP(B8,Catalogo!$A:$F,6,FALSE),0)) | G8: =IF(B8="","",E8*F8)
C9: =IF(B9="","",IFERROR(VLOOKUP(B9,Catalogo!$A:$F,2,FALSE),"CODIGO NO ENCONTRADO")) | D9: =IF(B9="","",IFERROR(VLOOKUP(B9,Catalogo!$A:$F,4,FALSE),"")) | F9: =IF(B9="","",IFERROR(VLOOKUP(B9,Catalogo!$A:$F,6,FALSE),0)) | G9: =IF(B9="","",E9*F9)
C10: =IF(B10="","",IFERROR(VLOOKUP(B10,Catalogo!$A:$F,2,FALSE),"CODIGO NO ENCONTRADO")) | D10: =IF(B10="","",IFERROR(VLOOKUP(B10,Catalogo!$A:$F,4,FALSE),"")) | F10: =IF(B10="","",IFERROR(VLOOKUP(B10,Catalogo!$A:$F,6,FALSE),0)) | G10: =IF(B10="","",E10*F10)
C11: =IF(B11="","",IFERROR(VLOOKUP(B11,Catalogo!$A:$F,2,FALSE),"CODIGO NO ENCONTRADO")) | D11: =IF(B11="","",IFERROR(VLOOKUP(B11,Catalogo!$A:$F,4,FALSE),"")) | F11: =IF(B11="","",IFERROR(VLOOKUP(B11,Catalogo!$A:$F,6,FALSE),0)) | G11: =IF(B11="","",E11*F11)
C12: =IF(B12="","",IFERROR(VLOOKUP(B12,Catalogo!$A:$F,2,FALSE),"CODIGO NO ENCONTRADO")) | D12: =IF(B12="","",IFERROR(VLOOKUP(B12,Catalogo!$A:$F,4,FALSE),"")) | F12: =IF(B12="","",IFERROR(VLOOKUP(B12,Catalogo!$A:$F,6,FALSE),0)) | G12: =IF(B12="","",E12*F12)
C13: =IF(B13="","",IFERROR(VLOOKUP(B13,Catalogo!$A:$F,2,FALSE),"CODIGO NO ENCONTRADO")) | D13: =IF(B13="","",IFERROR(VLOOKUP(B13,Catalogo!$A:$F,4,FALSE),"")) | F13: =IF(B13="","",IFERROR(VLOOKUP(B13,Catalogo!$A:$F,6,FALSE),0)) | G13: =IF(B13="","",E13*F13)
... C301: =IF(B301="","",IFERROR(VLOOKUP(B301,Catalogo!$A:$F,2,FALSE),"CODIGO NO ENCONTRADO")) | D301: =IF(B301="","",IFERROR(VLOOKUP(B301,Catalogo!$A:$F,4,FALSE),"")) | F301: =IF(B301="","",IFERROR(VLOOKUP(B301,Catalogo!$A:$F,6,FALSE),0)) | G301: =IF(B301="","",E301*F301)

Sheet Resumen
A1: Costo directo | B1: =SUM(Presupuesto!G2:G301)
A2: Administracion | B2: =B1*Proyecto!B8
A3: Imprevistos | B3: =B1*Proyecto!B9
A4: Utilidad | B4: =B1*Proyecto!B10
A5: Subtotal | B5: =SUM(B1:B4)
A6: IVA | B6: =IF(Proyecto!B12="SI",B4*Proyecto!B11,B5*Proyecto!B11)
A7: TOTAL | B7: =B5+B6
A8: Anticipo | B8: =B7*Proyecto!B13
A10: Costo directo por capitulo
B11: =IF(A11="","",SUMIF(Presupuesto!$A$2:$A$301,A11,Presupuesto!$G$2:$G$301))
B12: =IF(A12="","",SUMIF(Presupuesto!$A$2:$A$301,A12,Presupuesto!$G$2:$G$301))
B13: =IF(A13="","",SUMIF(Presupuesto!$A$2:$A$301,A13,Presupuesto!$G$2:$G$301))
B14: =IF(A14="","",SUMIF(Presupuesto!$A$2:$A$301,A14,Presupuesto!$G$2:$G$301))
B15: =IF(A15="","",SUMIF(Presupuesto!$A$2:$A$301,A15,Presupuesto!$G$2:$G$301))
B16: =IF(A16="","",SUMIF(Presupuesto!$A$2:$A$301,A16,Presupuesto!$G$2:$G$301))
B17: =IF(A17="","",SUMIF(Presupuesto!$A$2:$A$301,A17,Presupuesto!$G$2:$G$301))
B18: =IF(A18="","",SUMIF(Presupuesto!$A$2:$A$301,A18,Presupuesto!$G$2:$G$301))
B19: =IF(A19="","",SUMIF(Presupuesto!$A$2:$A$301,A19,Presupuesto!$G$2:$G$301))
B20: =IF(A20="","",SUMIF(Presupuesto!$A$2:$A$301,A20,Presupuesto!$G$2:$G$301))
B21: =IF(A21="","",SUMIF(Presupuesto!$A$2:$A$301,A21,Presupuesto!$G$2:$G$301))
B22: =IF(A22="","",SUMIF(Presupuesto!$A$2:$A$301,A22,Presupuesto!$G$2:$G$301))
... B30: =IF(A30="","",SUMIF(Presupuesto!$A$2:$A$301,A30,Presupuesto!$G$2:$G$301))

Sheet Cortes
A1: Mueble / Elemento | B1: Material (codigo) | C1: Largo mm | D1: Ancho mm | E1: Cantidad | F1: Rota? (SI/NO) | G1: Canto largo | H1: Canto ancho | I1: Notas | K1: Lamina estandar (mm)
K2: Largo | L2: 2440
K3: Ancho | L3: 1830
K4: Espesor sierra | L4: 4

Sheet Import_Odoo
A1: Order Lines/Product | B1: Order Lines/Description | C1: Order Lines/Quantity | D1: Order Lines/Unit Price | E1: Order Lines/Unit of Measure | G1: Nota: al importar, el nombre del producto debe coincidir con Odoo; ajustaremos columnas cuando exporte un ejemplo de su Odoo.
A2: =IF(Presupuesto!B2="","",Presupuesto!B2) | B2: =IF(Presupuesto!B2="","",Presupuesto!C2) | C2: =IF(Presupuesto!B2="","",Presupuesto!E2) | D2: =IF(Presupuesto!B2="","",Presupuesto!F2) | E2: =IF(Presupuesto!B2="","",Presupuesto!D2)
A3: =IF(Presupuesto!B3="","",Presupuesto!B3) | B3: =IF(Presupuesto!B3="","",Presupuesto!C3) | C3: =IF(Presupuesto!B3="","",Presupuesto!E3) | D3: =IF(Presupuesto!B3="","",Presupuesto!F3) | E3: =IF(Presupuesto!B3="","",Presupuesto!D3)
A4: =IF(Presupuesto!B4="","",Presupuesto!B4) | B4: =IF(Presupuesto!B4="","",Presupuesto!C4) | C4: =IF(Presupuesto!B4="","",Presupuesto!E4) | D4: =IF(Presupuesto!B4="","",Presupuesto!F4) | E4: =IF(Presupuesto!B4="","",Presupuesto!D4)
A5: =IF(Presupuesto!B5="","",Presupuesto!B5) | B5: =IF(Presupuesto!B5="","",Presupuesto!C5) | C5: =IF(Presupuesto!B5="","",Presupuesto!E5) | D5: =IF(Presupuesto!B5="","",Presupuesto!F5) | E5: =IF(Presupuesto!B5="","",Presupuesto!D5)
A6: =IF(Presupuesto!B6="","",Presupuesto!B6) | B6: =IF(Presupuesto!B6="","",Presupuesto!C6) | C6: =IF(Presupuesto!B6="","",Presupuesto!E6) | D6: =IF(Presupuesto!B6="","",Presupuesto!F6) | E6: =IF(Presupuesto!B6="","",Presupuesto!D6)
A7: =IF(Presupuesto!B7="","",Presupuesto!B7) | B7: =IF(Presupuesto!B7="","",Presupuesto!C7) | C7: =IF(Presupuesto!B7="","",Presupuesto!E7) | D7: =IF(Presupuesto!B7="","",Presupuesto!F7) | E7: =IF(Presupuesto!B7="","",Presupuesto!D7)
A8: =IF(Presupuesto!B8="","",Presupuesto!B8) | B8: =IF(Presupuesto!B8="","",Presupuesto!C8) | C8: =IF(Presupuesto!B8="","",Presupuesto!E8) | D8: =IF(Presupuesto!B8="","",Presupuesto!F8) | E8: =IF(Presupuesto!B8="","",Presupuesto!D8)
A9: =IF(Presupuesto!B9="","",Presupuesto!B9) | B9: =IF(Presupuesto!B9="","",Presupuesto!C9) | C9: =IF(Presupuesto!B9="","",Presupuesto!E9) | D9: =IF(Presupuesto!B9="","",Presupuesto!F9) | E9: =IF(Presupuesto!B9="","",Presupuesto!D9)
A10: =IF(Presupuesto!B10="","",Presupuesto!B10) | B10: =IF(Presupuesto!B10="","",Presupuesto!C10) | C10: =IF(Presupuesto!B10="","",Presupuesto!E10) | D10: =IF(Presupuesto!B10="","",Presupuesto!F10) | E10: =IF(Presupuesto!B10="","",Presupuesto!D10)
A11: =IF(Presupuesto!B11="","",Presupuesto!B11) | B11: =IF(Presupuesto!B11="","",Presupuesto!C11) | C11: =IF(Presupuesto!B11="","",Presupuesto!E11) | D11: =IF(Presupuesto!B11="","",Presupuesto!F11) | E11: =IF(Presupuesto!B11="","",Presupuesto!D11)
A12: =IF(Presupuesto!B12="","",Presupuesto!B12) | B12: =IF(Presupuesto!B12="","",Presupuesto!C12) | C12: =IF(Presupuesto!B12="","",Presupuesto!E12) | D12: =IF(Presupuesto!B12="","",Presupuesto!F12) | E12: =IF(Presupuesto!B12="","",Presupuesto!D12)
A13: =IF(Presupuesto!B13="","",Presupuesto!B13) | B13: =IF(Presupuesto!B13="","",Presupuesto!C13) | C13: =IF(Presupuesto!B13="","",Presupuesto!E13) | D13: =IF(Presupuesto!B13="","",Presupuesto!F13) | E13: =IF(Presupuesto!B13="","",Presupuesto!D13)
... A301: =IF(Presupuesto!B301="","",Presupuesto!B301) | B301: =IF(Presupuesto!B301="","",Presupuesto!C301) | C301: =IF(Presupuesto!B301="","",Presupuesto!E301) | D301: =IF(Presupuesto!B301="","",Presupuesto!F301) | E301: =IF(Presupuesto!B301="","",Presupuesto!D301)
