Workbook

Sheet Resumen
A1: RESUMEN DEL PRESUPUESTO - VERSION 0.1 (INCOMPLETA)
A2: Los items 'Pendiente' tienen costo 0 hasta que se cargue su precio en la hoja Catalogo.
A4: Capitulo | B4: Costo | C4: Venta (antes de IVA) | D4: Margen bruto
A5: 1. Divisiones de vidrio | B5: =SUMIF(Presupuesto!$A$2:$A$35,A5,Presupuesto!$H$2:$H$35) | C5: =SUMIF(Presupuesto!$A$2:$A$35,A5,Presupuesto!$I$2:$I$35) | D5: =IF(C5>0,(C5-B5)/C5,"")
A6: 2. Puertas y herrajes | B6: =SUMIF(Presupuesto!$A$2:$A$35,A6,Presupuesto!$H$2:$H$35) | C6: =SUMIF(Presupuesto!$A$2:$A$35,A6,Presupuesto!$I$2:$I$35) | D6: =IF(C6>0,(C6-B6)/C6,"")
A7: 3. Mobiliario en madera y accesorios | B7: =SUMIF(Presupuesto!$A$2:$A$35,A7,Presupuesto!$H$2:$H$35) | C7: =SUMIF(Presupuesto!$A$2:$A$35,A7,Presupuesto!$I$2:$I$35) | D7: =IF(C7>0,(C7-B7)/C7,"")
A8: 4. Estructuras metalicas | B8: =SUMIF(Presupuesto!$A$2:$A$35,A8,Presupuesto!$H$2:$H$35) | C8: =SUMIF(Presupuesto!$A$2:$A$35,A8,Presupuesto!$I$2:$I$35) | D8: =IF(C8>0,(C8-B8)/C8,"")
A9: 5. Sillas y complementos | B9: =SUMIF(Presupuesto!$A$2:$A$35,A9,Presupuesto!$H$2:$H$35) | C9: =SUMIF(Presupuesto!$A$2:$A$35,A9,Presupuesto!$I$2:$I$35) | D9: =IF(C9>0,(C9-B9)/C9,"")
A10: SUBTOTAL | B10: =SUM(B5:B9) | C10: =SUM(C5:C9) | D10: =IF(C10>0,(C10-B10)/C10,"")
A11: IVA | C11: =C10*Proyecto!$B$10
A12: TOTAL | C12: =C10+C11
A13: Anticipo | C13: =C12*Proyecto!$B$11
A15: Items con precio pendiente (no incluidos en totales) | B15: =COUNTIF(Presupuesto!$J$2:$J$35,"Pendiente")
A16: Margen objetivo aplicado a items con costo | B16: =Proyecto!$B$9
A17: Items con precio de venta definido por usted (sillas, sofa, mesa) conservan su precio y su margen real.

Sheet Proyecto
A1: PARAMETROS DEL PROYECTO
A3: Cliente
A4: NIT / Cedula
A5: Contacto
A6: Proyecto | B6: Oficinas - divisiones interiores y mobiliario
A7: Ciudad
A8: Fecha | B8: 46302
A9: Margen bruto objetivo (sobre precio de venta) | B9: 0.45 | C9: Venta = Costo / (1 - margen). Si usted lo define como recargo sobre costo, cambie la formula en Presupuesto!G.
A10: IVA | B10: 0.19 | C10: Ejemplo editable: confirmar con contador.
A11: Anticipo | B11: 0.5
A12: Altura de divisiones de vidrio (m) | B12: 2.42 | C12: Dato del cliente.
A13: Altura de puertas (m) | B13: 2.1 | C13: SUPUESTO: las puertas no llegan al cielo raso; confirmar.
A14: Ancho maximo de panel de vidrio (m) | B14: 1.2 | C14: Dato del cliente.
A15: Angulos de perfil L por borde (piso y techo) | B15: 2 | C15: SUPUESTO: un angulo por cada cara del vidrio.
A16: % del vidrio con serigrafia / pelicula | B16: 1 | C16: SUPUESTO: 100% del vidrio lleva serigrafia.

Sheet Calculo_Vidrio
A1: CALCULO DE VIDRIO, PERFILERIA Y PUERTAS
A2: Longitudes leidas del plano (aprox.). Confirmar en obra. Celdas amarillas editables.
A3: Espacio | B3: Tramo | C3: Largo total (m) | D3: Ancho puerta (m) | E3: Tipo puerta | F3: Largo fijo (m) | G3: Panos fijos | H3: Area total (m2) | I3: Area vidrio fijo (m2) | J3: Area hojas puerta (m2) | K3: Area sobre puerta (m2)
A4: Gerencia | B4: Pared al pasillo | C4: 4 | D4: 1.37 | E4: Corrediza | F4: =C4-D4 | G4: =IF(F4>0,ROUNDUP(F4/Proyecto!$B$14,0),0) | H4: =C4*Proyecto!$B$12 | I4: =F4*Proyecto!$B$12 | J4: =D4*Proyecto!$B$13 | K4: =D4*(Proyecto!$B$12-Proyecto!$B$13)
A5: Gerencia | B5: Pared con Admin 1 | C5: 2.49 | D5: 0 | F5: =C5-D5 | G5: =IF(F5>0,ROUNDUP(F5/Proyecto!$B$14,0),0) | H5: =C5*Proyecto!$B$12 | I5: =F5*Proyecto!$B$12 | J5: =D5*Proyecto!$B$13 | K5: =D5*(Proyecto!$B$12-Proyecto!$B$13)
A6: Admin 1 | B6: Pared al pasillo | C6: 2.23 | D6: 0.75 | E6: Batiente | F6: =C6-D6 | G6: =IF(F6>0,ROUNDUP(F6/Proyecto!$B$14,0),0) | H6: =C6*Proyecto!$B$12 | I6: =F6*Proyecto!$B$12 | J6: =D6*Proyecto!$B$13 | K6: =D6*(Proyecto!$B$12-Proyecto!$B$13)
A7: Admin 1 | B7: Pared con Admin 2 | C7: 2.48 | D7: 0 | F7: =C7-D7 | G7: =IF(F7>0,ROUNDUP(F7/Proyecto!$B$14,0),0) | H7: =C7*Proyecto!$B$12 | I7: =F7*Proyecto!$B$12 | J7: =D7*Proyecto!$B$13 | K7: =D7*(Proyecto!$B$12-Proyecto!$B$13)
A8: Admin 2 | B8: Pared al pasillo | C8: 2.44 | D8: 0.75 | E8: Batiente | F8: =C8-D8 | G8: =IF(F8>0,ROUNDUP(F8/Proyecto!$B$14,0),0) | H8: =C8*Proyecto!$B$12 | I8: =F8*Proyecto!$B$12 | J8: =D8*Proyecto!$B$13 | K8: =D8*(Proyecto!$B$12-Proyecto!$B$13)
A9: Admin 2 | B9: Pared sur | C9: 2.49 | D9: 0 | F9: =C9-D9 | G9: =IF(F9>0,ROUNDUP(F9/Proyecto!$B$14,0),0) | H9: =C9*Proyecto!$B$12 | I9: =F9*Proyecto!$B$12 | J9: =D9*Proyecto!$B$13 | K9: =D9*(Proyecto!$B$12-Proyecto!$B$13)
A10: Sala juntas | B10: Pared al pasillo | C10: 3.43 | D10: 1.56 | E10: Corrediza | F10: =C10-D10 | G10: =IF(F10>0,ROUNDUP(F10/Proyecto!$B$14,0),0) | H10: =C10*Proyecto!$B$12 | I10: =F10*Proyecto!$B$12 | J10: =D10*Proyecto!$B$13 | K10: =D10*(Proyecto!$B$12-Proyecto!$B$13)
A11: Sala juntas | B11: Pared norte | C11: 1.09 | D11: 0 | F11: =C11-D11 | G11: =IF(F11>0,ROUNDUP(F11/Proyecto!$B$14,0),0) | H11: =C11*Proyecto!$B$12 | I11: =F11*Proyecto!$B$12 | J11: =D11*Proyecto!$B$13 | K11: =D11*(Proyecto!$B$12-Proyecto!$B$13)
A12: Sala juntas | B12: Pared sur | C12: 2.42 | D12: 0 | F12: =C12-D12 | G12: =IF(F12>0,ROUNDUP(F12/Proyecto!$B$14,0),0) | H12: =C12*Proyecto!$B$12 | I12: =F12*Proyecto!$B$12 | J12: =D12*Proyecto!$B$13 | K12: =D12*(Proyecto!$B$12-Proyecto!$B$13)
A13: TOTAL | C13: =SUM(C4:C12) | D13: =SUM(D4:D12) | F13: =SUM(F4:F12) | G13: =SUM(G4:G12) | H13: =SUM(H4:H12) | I13: =SUM(I4:I12) | J13: =SUM(J4:J12) | K13: =SUM(K4:K12)
A15: Perfil L 1x1 aluminio - piso (ml) | C15: =F13*Proyecto!$B$15
A16: Perfil L 1x1 aluminio - techo (ml) | C16: =C13*Proyecto!$B$15
A17: Perfil L 1x1 aluminio - TOTAL (ml) | C17: =C15+C16
A18: Silicona entre panos (ml) | C18: =SUMPRODUCT((G4:G12>1)*(G4:G12-1))*Proyecto!$B$12
A21: Puerta | B21: Tipo | C21: Ancho total (m) | D21: Hojas | E21: Alto (m) | F21: Marco aluminio (ml) | G21: Bisagras | H21: Manijas | I21: Topes | J21: Chapa pico de loro | K21: Pasador | L21: Sistema corredizo
A22: Gerencia | B22: Corrediza doble | C22: 1.37 | D22: 2 | E22: =Proyecto!$B$13 | F22: =D22*2*(C22/D22+E22) | G22: 0 | H22: 2 | I22: 2 | J22: 1 | K22: 0 | L22: 1
A23: Sala juntas | B23: Corrediza doble | C23: 1.56 | D23: 2 | E23: =Proyecto!$B$13 | F23: =D23*2*(C23/D23+E23) | G23: 0 | H23: 2 | I23: 2 | J23: 1 | K23: 0 | L23: 1
A24: Admin 1 | B24: Batiente | C24: 0.75 | D24: 1 | E24: =Proyecto!$B$13 | F24: =D24*2*(C24/D24+E24) | G24: 3 | H24: 2 | I24: 1 | J24: 0 | K24: 1 | L24: 0
A25: Admin 2 | B25: Batiente | C25: 0.75 | D25: 1 | E25: =Proyecto!$B$13 | F25: =D25*2*(C25/D25+E25) | G25: 3 | H25: 2 | I25: 1 | J25: 0 | K25: 1 | L25: 0
A26: TOTAL | C26: =SUM(C22:C25) | F26: =SUM(F22:F25) | G26: =SUM(G22:G25) | H26: =SUM(H22:H25) | I26: =SUM(I22:I25) | J26: =SUM(J22:J25) | K26: =SUM(K22:K25) | L26: =SUM(L22:L25)
A28: Notas: 137 cm y 156 cm se tomaron como ancho TOTAL del vano (ambas alas). Cantidades de herrajes son SUPUESTOS a confirmar.

Sheet Cortes_Tablero
A1: OPTIMIZACION DE CORTE - TABLERO 15 mm (2.15 x 2.44 m, Madecentro)
A2: Tapas en sandwich 15+15 mm (3 cm): cada tapa lleva 2 capas. Corte guillotina, sierra 4 mm, rotacion permitida.
A4: Pieza | B4: Largo (mm) | C4: Ancho (mm) | D4: Tapas | E4: Capas | F4: Total piezas | G4: Area (m2)
A5: Admin L - brazo 1.50x0.60 | B5: 1500 | C5: 600 | D5: 2 | E5: 2 | F5: =D5*E5 | G5: =B5*C5/1000000*F5
A6: Admin L - brazo 0.90x0.60 | B6: 900 | C6: 600 | D6: 2 | E6: 2 | F6: =D6*E6 | G6: =B6*C6/1000000*F6
A7: Gerencia - frente 1.70x0.75 | B7: 1700 | C7: 750 | D7: 1 | E7: 2 | F7: =D7*E7 | G7: =B7*C7/1000000*F7
A8: Gerencia - retorno 0.95x0.60 | B8: 950 | C8: 600 | D8: 1 | E8: 2 | F8: =D8*E8 | G8: =B8*C8/1000000*F8
A9: Mesa juntas 1.76x1.15 | B9: 1760 | C9: 1150 | D9: 1 | E9: 2 | F9: =D9*E9 | G9: =B9*C9/1000000*F9
A10: Isla - puesto 1.37x0.60 | B10: 1370 | C10: 600 | D10: 6 | E10: 2 | F10: =D10*E10 | G10: =B10*C10/1000000*F10
A11: TOTAL | F11: =SUM(F5:F10) | G11: =SUM(G5:G10)
A13: Tapas armadas y canto rigido 3 cm (todos los bordes)
A14: Tapa | B14: Cantidad | C14: Perimetro c/u (m) | D14: Canto total (ml) | E14: Area 1 capa c/u (m2)
A15: Escritorio admin L 1.50x1.50 (60 cm) | B15: 2 | C15: 6 | D15: =B15*C15 | E15: 1.44
A16: Escritorio gerencia L (1.70x0.75 + retorno 1.70x0.60) | B16: 1 | C16: 6.8 | D16: =B16*C16 | E16: 1.845
A17: Mesa de juntas 1.76x1.15 | B17: 1 | C17: 5.82 | D17: =B17*C17 | E17: 2.024
A18: Isla - puesto de trabajo 1.37x0.60 | B18: 6 | C18: 3.94 | D18: =B18*C18 | E18: 0.822
A19: TOTAL | D19: =SUM(D15:D18) | E19: =SUMPRODUCT(B15:B18,E15:E18)
A21: RESULTADO DE LA OPTIMIZACION
A22: Hojas necesarias (resultado del optimizador) | B22: 6
A23: Hojas minimas teoricas (area piezas / area hoja) | B23: =G11/(2.15*2.44)
A24: Aprovechamiento sobre las hojas compradas | B24: =G11/(B22*2.15*2.44)
A26: Nota: la hoja 6 solo lleva 1 pieza (0.90x0.60, capa inferior oculta). Si esa capa se arma con retales de otras hojas, se compran 5 hojas.

Sheet Cortes_Tubo
A1: OPTIMIZACION DE CORTE - TUBO CUADRADO 2x2" CAL. 18 (barras de 6 m)
A2: Supuesto de diseno: perimetro bajo la tapa + 4 patas de 70 cm + travesanos. Sierra 3 mm.
A4: Barra | B4: Cortes (mm) | C4: Usado (mm) | D4: Sobrante (mm)
A5: 1 | B5: 4000 (Isla) + 1760 (Mesa juntas) | C5: 5763 | D5: 237
A6: 2 | B6: 4000 (Isla) + 1760 (Mesa juntas) | C6: 5763 | D6: 237
A7: 3 | B7: 4000 (Isla) + 1700 (Gerencia) | C7: 5703 | D7: 297
A8: 4 | B8: 1700 (Gerencia) + 1500 (Admin) + 1500 (Admin) + 1200 (Isla) | C8: 5909 | D8: 91
A9: 5 | B9: 1500 (Admin) + 1500 (Admin) + 1200 (Isla) + 1150 (Mesa juntas) + 600 (Admin) | C9: 5962 | D9: 38
A10: 6 | B10: 1150 (Mesa juntas) + 1100 (Gerencia) + 1050 (Mesa juntas) + 1050 (Mesa juntas) + 950 (Gerencia) + 600 (Admin) | C10: 5915 | D10: 85
A11: 7 | B11: 900 (Admin) + 900 (Admin) + 900 (Admin) + 900 (Admin) + 750 (Gerencia) + 700 (Admin) + 700 (Admin) | C11: 5768 | D11: 232
A12: 8 | B12: 700 (Admin) + 700 (Admin) + 700 (Admin) + 700 (Admin) + 700 (Admin) + 700 (Admin) + 700 (Gerencia) + 700 (Gerencia) | C12: 5621 | D12: 379
A13: 9 | B13: 700 (Gerencia) + 700 (Gerencia) + 700 (Mesa juntas) + 700 (Mesa juntas) + 700 (Mesa juntas) + 700 (Mesa juntas) + 700 (Isla) + 700 (Isla) | C13: 5621 | D13: 379
A14: 10 | B14: 700 (Isla) + 700 (Isla) + 600 (Admin) + 600 (Admin) + 600 (Gerencia) | C14: 3212 | D14: 2788
A15: Total | B15: Metros lineales de corte: 55.12 m
A16: Barras | B16: 10

Sheet Presupuesto
A1: Capitulo | B1: Codigo | C1: Descripcion | D1: UdM | E1: Cantidad | F1: Costo unit. | G1: Venta unit. | H1: Costo total | I1: Venta total | J1: Estado precio | K1: Margen % | L1: Observacion
A2: 1. Divisiones de vidrio
A3: 1. Divisiones de vidrio | B3: VID-SER-10 | C3: =IFERROR(VLOOKUP($B3,Catalogo!$A:$J,2,FALSE),"CODIGO NO ENCONTRADO") | D3: =IFERROR(VLOOKUP($B3,Catalogo!$A:$J,4,FALSE),"") | E3: =Calculo_Vidrio!H13*Proyecto!$B$16 | F3: =IFERROR(N(VLOOKUP($B3,Catalogo!$A:$J,5,FALSE)),0) | G3: =IFERROR(IF(N(VLOOKUP($B3,Catalogo!$A:$J,6,FALSE))>0,VLOOKUP($B3,Catalogo!$A:$J,6,FALSE),IF(F3>0,F3/(1-Proyecto!$B$9),0)),0) | H3: =E3*F3 | I3: =E3*G3 | J3: =IFERROR(VLOOKUP($B3,Catalogo!$A:$J,9,FALSE),"") | K3: =IF(I3>0,(I3-H3)/I3,"") | L3: Incluye hojas de puerta y paños sobre puertas. Negro gerencia / blanco resto.
A4: 1. Divisiones de vidrio | B4: VID-TEM-10 | C4: =IFERROR(VLOOKUP($B4,Catalogo!$A:$J,2,FALSE),"CODIGO NO ENCONTRADO") | D4: =IFERROR(VLOOKUP($B4,Catalogo!$A:$J,4,FALSE),"") | E4: =Calculo_Vidrio!H13*(1-Proyecto!$B$16) | F4: =IFERROR(N(VLOOKUP($B4,Catalogo!$A:$J,5,FALSE)),0) | G4: =IFERROR(IF(N(VLOOKUP($B4,Catalogo!$A:$J,6,FALSE))>0,VLOOKUP($B4,Catalogo!$A:$J,6,FALSE),IF(F4>0,F4/(1-Proyecto!$B$9),0)),0) | H4: =E4*F4 | I4: =E4*G4 | J4: =IFERROR(VLOOKUP($B4,Catalogo!$A:$J,9,FALSE),"") | K4: =IF(I4>0,(I4-H4)/I4,"") | L4: Vidrio transparente (si no todo lleva serigrafia).
A5: 1. Divisiones de vidrio | B5: PER-L1-AL | C5: =IFERROR(VLOOKUP($B5,Catalogo!$A:$J,2,FALSE),"CODIGO NO ENCONTRADO") | D5: =IFERROR(VLOOKUP($B5,Catalogo!$A:$J,4,FALSE),"") | E5: =Calculo_Vidrio!C17 | F5: =IFERROR(N(VLOOKUP($B5,Catalogo!$A:$J,5,FALSE)),0) | G5: =IFERROR(IF(N(VLOOKUP($B5,Catalogo!$A:$J,6,FALSE))>0,VLOOKUP($B5,Catalogo!$A:$J,6,FALSE),IF(F5>0,F5/(1-Proyecto!$B$9),0)),0) | H5: =E5*F5 | I5: =E5*G5 | J5: =IFERROR(VLOOKUP($B5,Catalogo!$A:$J,9,FALSE),"") | K5: =IF(I5>0,(I5-H5)/I5,"") | L5: 2 angulos por borde, piso y techo.
A6: 1. Divisiones de vidrio | B6: SIL-EST | C6: =IFERROR(VLOOKUP($B6,Catalogo!$A:$J,2,FALSE),"CODIGO NO ENCONTRADO") | D6: =IFERROR(VLOOKUP($B6,Catalogo!$A:$J,4,FALSE),"") | E6: =Calculo_Vidrio!C18 | F6: =IFERROR(N(VLOOKUP($B6,Catalogo!$A:$J,5,FALSE)),0) | G6: =IFERROR(IF(N(VLOOKUP($B6,Catalogo!$A:$J,6,FALSE))>0,VLOOKUP($B6,Catalogo!$A:$J,6,FALSE),IF(F6>0,F6/(1-Proyecto!$B$9),0)),0) | H6: =E6*F6 | I6: =E6*G6 | J6: =IFERROR(VLOOKUP($B6,Catalogo!$A:$J,9,FALSE),"") | K6: =IF(I6>0,(I6-H6)/I6,"") | L6: Union entre panos.
A7: 1. Divisiones de vidrio | B7: MO-VID-INST | C7: =IFERROR(VLOOKUP($B7,Catalogo!$A:$J,2,FALSE),"CODIGO NO ENCONTRADO") | D7: =IFERROR(VLOOKUP($B7,Catalogo!$A:$J,4,FALSE),"") | E7: =Calculo_Vidrio!H13 | F7: =IFERROR(N(VLOOKUP($B7,Catalogo!$A:$J,5,FALSE)),0) | G7: =IFERROR(IF(N(VLOOKUP($B7,Catalogo!$A:$J,6,FALSE))>0,VLOOKUP($B7,Catalogo!$A:$J,6,FALSE),IF(F7>0,F7/(1-Proyecto!$B$9),0)),0) | H7: =E7*F7 | I7: =E7*G7 | J7: =IFERROR(VLOOKUP($B7,Catalogo!$A:$J,9,FALSE),"") | K7: =IF(I7>0,(I7-H7)/I7,"") | L7: Subcontratista, $/m2 instalado.
A8: 1. Divisiones de vidrio | B8: BOQ-VID | C8: =IFERROR(VLOOKUP($B8,Catalogo!$A:$J,2,FALSE),"CODIGO NO ENCONTRADO") | D8: =IFERROR(VLOOKUP($B8,Catalogo!$A:$J,4,FALSE),"") | E8: =Calculo_Vidrio!J26 | F8: =IFERROR(N(VLOOKUP($B8,Catalogo!$A:$J,5,FALSE)),0) | G8: =IFERROR(IF(N(VLOOKUP($B8,Catalogo!$A:$J,6,FALSE))>0,VLOOKUP($B8,Catalogo!$A:$J,6,FALSE),IF(F8>0,F8/(1-Proyecto!$B$9),0)),0) | H8: =E8*F8 | I8: =E8*G8 | J8: =IFERROR(VLOOKUP($B8,Catalogo!$A:$J,9,FALSE),"") | K8: =IF(I8>0,(I8-H8)/I8,"") | L8: Boquete por chapa pico de loro (provisional).
A9: 1. Divisiones de vidrio | B9: ORI-VID | C9: =IFERROR(VLOOKUP($B9,Catalogo!$A:$J,2,FALSE),"CODIGO NO ENCONTRADO") | D9: =IFERROR(VLOOKUP($B9,Catalogo!$A:$J,4,FALSE),"") | E9: =Calculo_Vidrio!K26*2 | F9: =IFERROR(N(VLOOKUP($B9,Catalogo!$A:$J,5,FALSE)),0) | G9: =IFERROR(IF(N(VLOOKUP($B9,Catalogo!$A:$J,6,FALSE))>0,VLOOKUP($B9,Catalogo!$A:$J,6,FALSE),IF(F9>0,F9/(1-Proyecto!$B$9),0)),0) | H9: =E9*F9 | I9: =E9*G9 | J9: =IFERROR(VLOOKUP($B9,Catalogo!$A:$J,9,FALSE),"") | K9: =IF(I9>0,(I9-H9)/I9,"") | L9: 2 orificios por pasador (provisional).
A10: 2. Puertas y herrajes
A11: 2. Puertas y herrajes | B11: PTA-MARCO-AL | C11: =IFERROR(VLOOKUP($B11,Catalogo!$A:$J,2,FALSE),"CODIGO NO ENCONTRADO") | D11: =IFERROR(VLOOKUP($B11,Catalogo!$A:$J,4,FALSE),"") | E11: =Calculo_Vidrio!F26 | F11: =IFERROR(N(VLOOKUP($B11,Catalogo!$A:$J,5,FALSE)),0) | G11: =IFERROR(IF(N(VLOOKUP($B11,Catalogo!$A:$J,6,FALSE))>0,VLOOKUP($B11,Catalogo!$A:$J,6,FALSE),IF(F11>0,F11/(1-Proyecto!$B$9),0)),0) | H11: =E11*F11 | I11: =E11*G11 | J11: =IFERROR(VLOOKUP($B11,Catalogo!$A:$J,9,FALSE),"") | K11: =IF(I11>0,(I11-H11)/I11,"") | L11: Marco aluminio para las 4 puertas.
A12: 2. Puertas y herrajes | B12: PTA-CORR | C12: =IFERROR(VLOOKUP($B12,Catalogo!$A:$J,2,FALSE),"CODIGO NO ENCONTRADO") | D12: =IFERROR(VLOOKUP($B12,Catalogo!$A:$J,4,FALSE),"") | E12: =Calculo_Vidrio!L26 | F12: =IFERROR(N(VLOOKUP($B12,Catalogo!$A:$J,5,FALSE)),0) | G12: =IFERROR(IF(N(VLOOKUP($B12,Catalogo!$A:$J,6,FALSE))>0,VLOOKUP($B12,Catalogo!$A:$J,6,FALSE),IF(F12>0,F12/(1-Proyecto!$B$9),0)),0) | H12: =E12*F12 | I12: =E12*G12 | J12: =IFERROR(VLOOKUP($B12,Catalogo!$A:$J,9,FALSE),"") | K12: =IF(I12>0,(I12-H12)/I12,"") | L12: Gerencia y sala de juntas.
A13: 2. Puertas y herrajes | B13: PTA-BIS | C13: =IFERROR(VLOOKUP($B13,Catalogo!$A:$J,2,FALSE),"CODIGO NO ENCONTRADO") | D13: =IFERROR(VLOOKUP($B13,Catalogo!$A:$J,4,FALSE),"") | E13: =Calculo_Vidrio!G26 | F13: =IFERROR(N(VLOOKUP($B13,Catalogo!$A:$J,5,FALSE)),0) | G13: =IFERROR(IF(N(VLOOKUP($B13,Catalogo!$A:$J,6,FALSE))>0,VLOOKUP($B13,Catalogo!$A:$J,6,FALSE),IF(F13>0,F13/(1-Proyecto!$B$9),0)),0) | H13: =E13*F13 | I13: =E13*G13 | J13: =IFERROR(VLOOKUP($B13,Catalogo!$A:$J,9,FALSE),"") | K13: =IF(I13>0,(I13-H13)/I13,"") | L13: Puertas batientes administrativas.
A14: 2. Puertas y herrajes | B14: PTA-MAN | C14: =IFERROR(VLOOKUP($B14,Catalogo!$A:$J,2,FALSE),"CODIGO NO ENCONTRADO") | D14: =IFERROR(VLOOKUP($B14,Catalogo!$A:$J,4,FALSE),"") | E14: =Calculo_Vidrio!H26 | F14: =IFERROR(N(VLOOKUP($B14,Catalogo!$A:$J,5,FALSE)),0) | G14: =IFERROR(IF(N(VLOOKUP($B14,Catalogo!$A:$J,6,FALSE))>0,VLOOKUP($B14,Catalogo!$A:$J,6,FALSE),IF(F14>0,F14/(1-Proyecto!$B$9),0)),0) | H14: =E14*F14 | I14: =E14*G14 | J14: =IFERROR(VLOOKUP($B14,Catalogo!$A:$J,9,FALSE),"") | K14: =IF(I14>0,(I14-H14)/I14,"")
A15: 2. Puertas y herrajes | B15: PTA-TOPE | C15: =IFERROR(VLOOKUP($B15,Catalogo!$A:$J,2,FALSE),"CODIGO NO ENCONTRADO") | D15: =IFERROR(VLOOKUP($B15,Catalogo!$A:$J,4,FALSE),"") | E15: =Calculo_Vidrio!I26 | F15: =IFERROR(N(VLOOKUP($B15,Catalogo!$A:$J,5,FALSE)),0) | G15: =IFERROR(IF(N(VLOOKUP($B15,Catalogo!$A:$J,6,FALSE))>0,VLOOKUP($B15,Catalogo!$A:$J,6,FALSE),IF(F15>0,F15/(1-Proyecto!$B$9),0)),0) | H15: =E15*F15 | I15: =E15*G15 | J15: =IFERROR(VLOOKUP($B15,Catalogo!$A:$J,9,FALSE),"") | K15: =IF(I15>0,(I15-H15)/I15,"") | L15: Puertas no llegan al cielo raso.
A16: 2. Puertas y herrajes | B16: PTA-CHAPA-PL | C16: =IFERROR(VLOOKUP($B16,Catalogo!$A:$J,2,FALSE),"CODIGO NO ENCONTRADO") | D16: =IFERROR(VLOOKUP($B16,Catalogo!$A:$J,4,FALSE),"") | E16: =Calculo_Vidrio!J26 | F16: =IFERROR(N(VLOOKUP($B16,Catalogo!$A:$J,5,FALSE)),0) | G16: =IFERROR(IF(N(VLOOKUP($B16,Catalogo!$A:$J,6,FALSE))>0,VLOOKUP($B16,Catalogo!$A:$J,6,FALSE),IF(F16>0,F16/(1-Proyecto!$B$9),0)),0) | H16: =E16*F16 | I16: =E16*G16 | J16: =IFERROR(VLOOKUP($B16,Catalogo!$A:$J,9,FALSE),"") | K16: =IF(I16>0,(I16-H16)/I16,"") | L16: Gerencia y juntas.
A17: 2. Puertas y herrajes | B17: PTA-PAS | C17: =IFERROR(VLOOKUP($B17,Catalogo!$A:$J,2,FALSE),"CODIGO NO ENCONTRADO") | D17: =IFERROR(VLOOKUP($B17,Catalogo!$A:$J,4,FALSE),"") | E17: =Calculo_Vidrio!K26 | F17: =IFERROR(N(VLOOKUP($B17,Catalogo!$A:$J,5,FALSE)),0) | G17: =IFERROR(IF(N(VLOOKUP($B17,Catalogo!$A:$J,6,FALSE))>0,VLOOKUP($B17,Catalogo!$A:$J,6,FALSE),IF(F17>0,F17/(1-Proyecto!$B$9),0)),0) | H17: =E17*F17 | I17: =E17*G17 | J17: =IFERROR(VLOOKUP($B17,Catalogo!$A:$J,9,FALSE),"") | K17: =IF(I17>0,(I17-H17)/I17,"") | L17: Administrativas.
A18: 3. Mobiliario en madera y accesorios
A19: 3. Mobiliario en madera y accesorios | B19: TAB-15-215x244 | C19: =IFERROR(VLOOKUP($B19,Catalogo!$A:$J,2,FALSE),"CODIGO NO ENCONTRADO") | D19: =IFERROR(VLOOKUP($B19,Catalogo!$A:$J,4,FALSE),"") | E19: =Cortes_Tablero!B22 | F19: =IFERROR(N(VLOOKUP($B19,Catalogo!$A:$J,5,FALSE)),0) | G19: =IFERROR(IF(N(VLOOKUP($B19,Catalogo!$A:$J,6,FALSE))>0,VLOOKUP($B19,Catalogo!$A:$J,6,FALSE),IF(F19>0,F19/(1-Proyecto!$B$9),0)),0) | H19: =E19*F19 | I19: =E19*G19 | J19: =IFERROR(VLOOKUP($B19,Catalogo!$A:$J,9,FALSE),"") | K19: =IF(I19>0,(I19-H19)/I19,"") | L19: Segun optimizacion de corte (2 capas por tapa).
A20: 3. Mobiliario en madera y accesorios | B20: CANTO-3CM | C20: =IFERROR(VLOOKUP($B20,Catalogo!$A:$J,2,FALSE),"CODIGO NO ENCONTRADO") | D20: =IFERROR(VLOOKUP($B20,Catalogo!$A:$J,4,FALSE),"") | E20: =Cortes_Tablero!D19 | F20: =IFERROR(N(VLOOKUP($B20,Catalogo!$A:$J,5,FALSE)),0) | G20: =IFERROR(IF(N(VLOOKUP($B20,Catalogo!$A:$J,6,FALSE))>0,VLOOKUP($B20,Catalogo!$A:$J,6,FALSE),IF(F20>0,F20/(1-Proyecto!$B$9),0)),0) | H20: =E20*F20 | I20: =E20*G20 | J20: =IFERROR(VLOOKUP($B20,Catalogo!$A:$J,9,FALSE),"") | K20: =IF(I20>0,(I20-H20)/I20,"") | L20: Todos los bordes de cada tapa.
A21: 3. Mobiliario en madera y accesorios | B21: BOQ-GRM | C21: =IFERROR(VLOOKUP($B21,Catalogo!$A:$J,2,FALSE),"CODIGO NO ENCONTRADO") | D21: =IFERROR(VLOOKUP($B21,Catalogo!$A:$J,4,FALSE),"") | E21: 1 | F21: =IFERROR(N(VLOOKUP($B21,Catalogo!$A:$J,5,FALSE)),0) | G21: =IFERROR(IF(N(VLOOKUP($B21,Catalogo!$A:$J,6,FALSE))>0,VLOOKUP($B21,Catalogo!$A:$J,6,FALSE),IF(F21>0,F21/(1-Proyecto!$B$9),0)),0) | H21: =E21*F21 | I21: =E21*G21 | J21: =IFERROR(VLOOKUP($B21,Catalogo!$A:$J,9,FALSE),"") | K21: =IF(I21>0,(I21-H21)/I21,"") | L21: Mesa de juntas.
A22: 3. Mobiliario en madera y accesorios | B22: VID-TEM-10 | C22: =IFERROR(VLOOKUP($B22,Catalogo!$A:$J,2,FALSE),"CODIGO NO ENCONTRADO") | D22: =IFERROR(VLOOKUP($B22,Catalogo!$A:$J,4,FALSE),"") | E22: 2.21 | F22: =IFERROR(N(VLOOKUP($B22,Catalogo!$A:$J,5,FALSE)),0) | G22: =IFERROR(IF(N(VLOOKUP($B22,Catalogo!$A:$J,6,FALSE))>0,VLOOKUP($B22,Catalogo!$A:$J,6,FALSE),IF(F22>0,F22/(1-Proyecto!$B$9),0)),0) | H22: =E22*F22 | I22: =E22*G22 | J22: =IFERROR(VLOOKUP($B22,Catalogo!$A:$J,9,FALSE),"") | K22: =IF(I22>0,(I22-H22)/I22,"") | L22: Pantallas de vidrio 35 cm de la isla (4 laterales + 3 centrales).
A23: 3. Mobiliario en madera y accesorios | B23: ARCH-2X1 | C23: =IFERROR(VLOOKUP($B23,Catalogo!$A:$J,2,FALSE),"CODIGO NO ENCONTRADO") | D23: =IFERROR(VLOOKUP($B23,Catalogo!$A:$J,4,FALSE),"") | E23: 5 | F23: =IFERROR(N(VLOOKUP($B23,Catalogo!$A:$J,5,FALSE)),0) | G23: =IFERROR(IF(N(VLOOKUP($B23,Catalogo!$A:$J,6,FALSE))>0,VLOOKUP($B23,Catalogo!$A:$J,6,FALSE),IF(F23>0,F23/(1-Proyecto!$B$9),0)),0) | H23: =E23*F23 | I23: =E23*G23 | J23: =IFERROR(VLOOKUP($B23,Catalogo!$A:$J,9,FALSE),"") | K23: =IF(I23>0,(I23-H23)/I23,"") | L23: 2 admin + 1 gerencia + 2 isla (supuesto).
A24: 4. Estructuras metalicas
A25: 4. Estructuras metalicas | B25: TUB-2X2-C18 | C25: =IFERROR(VLOOKUP($B25,Catalogo!$A:$J,2,FALSE),"CODIGO NO ENCONTRADO") | D25: =IFERROR(VLOOKUP($B25,Catalogo!$A:$J,4,FALSE),"") | E25: =Cortes_Tubo!$B$16 | F25: =IFERROR(N(VLOOKUP($B25,Catalogo!$A:$J,5,FALSE)),0) | G25: =IFERROR(IF(N(VLOOKUP($B25,Catalogo!$A:$J,6,FALSE))>0,VLOOKUP($B25,Catalogo!$A:$J,6,FALSE),IF(F25>0,F25/(1-Proyecto!$B$9),0)),0) | H25: =E25*F25 | I25: =E25*G25 | J25: =IFERROR(VLOOKUP($B25,Catalogo!$A:$J,9,FALSE),"") | K25: =IF(I25>0,(I25-H25)/I25,"") | L25: Barras de 6 m segun optimizacion.
A26: 4. Estructuras metalicas | B26: PINT-ELEC | C26: =IFERROR(VLOOKUP($B26,Catalogo!$A:$J,2,FALSE),"CODIGO NO ENCONTRADO") | D26: =IFERROR(VLOOKUP($B26,Catalogo!$A:$J,4,FALSE),"") | E26: =55.12*0.2032 | F26: =IFERROR(N(VLOOKUP($B26,Catalogo!$A:$J,5,FALSE)),0) | G26: =IFERROR(IF(N(VLOOKUP($B26,Catalogo!$A:$J,6,FALSE))>0,VLOOKUP($B26,Catalogo!$A:$J,6,FALSE),IF(F26>0,F26/(1-Proyecto!$B$9),0)),0) | H26: =E26*F26 | I26: =E26*G26 | J26: =IFERROR(VLOOKUP($B26,Catalogo!$A:$J,9,FALSE),"") | K26: =IF(I26>0,(I26-H26)/I26,"") | L26: Area aprox. (perimetro del tubo 0.2032 m).
A27: 4. Estructuras metalicas | B27: CAN-ELEC-ISLA | C27: =IFERROR(VLOOKUP($B27,Catalogo!$A:$J,2,FALSE),"CODIGO NO ENCONTRADO") | D27: =IFERROR(VLOOKUP($B27,Catalogo!$A:$J,4,FALSE),"") | E27: 1 | F27: =IFERROR(N(VLOOKUP($B27,Catalogo!$A:$J,5,FALSE)),0) | G27: =IFERROR(IF(N(VLOOKUP($B27,Catalogo!$A:$J,6,FALSE))>0,VLOOKUP($B27,Catalogo!$A:$J,6,FALSE),IF(F27>0,F27/(1-Proyecto!$B$9),0)),0) | H27: =E27*F27 | I27: =E27*G27 | J27: =IFERROR(VLOOKUP($B27,Catalogo!$A:$J,9,FALSE),"") | K27: =IF(I27>0,(I27-H27)/I27,"") | L27: Canaletas y cableado estructurado de la isla.
A28: 5. Sillas y complementos
A29: 5. Sillas y complementos | B29: SIL-GER | C29: =IFERROR(VLOOKUP($B29,Catalogo!$A:$J,2,FALSE),"CODIGO NO ENCONTRADO") | D29: =IFERROR(VLOOKUP($B29,Catalogo!$A:$J,4,FALSE),"") | E29: 1 | F29: =IFERROR(N(VLOOKUP($B29,Catalogo!$A:$J,5,FALSE)),0) | G29: =IFERROR(IF(N(VLOOKUP($B29,Catalogo!$A:$J,6,FALSE))>0,VLOOKUP($B29,Catalogo!$A:$J,6,FALSE),IF(F29>0,F29/(1-Proyecto!$B$9),0)),0) | H29: =E29*F29 | I29: =E29*G29 | J29: =IFERROR(VLOOKUP($B29,Catalogo!$A:$J,9,FALSE),"") | K29: =IF(I29>0,(I29-H29)/I29,"")
A30: 5. Sillas y complementos | B30: SIL-ADM | C30: =IFERROR(VLOOKUP($B30,Catalogo!$A:$J,2,FALSE),"CODIGO NO ENCONTRADO") | D30: =IFERROR(VLOOKUP($B30,Catalogo!$A:$J,4,FALSE),"") | E30: 2 | F30: =IFERROR(N(VLOOKUP($B30,Catalogo!$A:$J,5,FALSE)),0) | G30: =IFERROR(IF(N(VLOOKUP($B30,Catalogo!$A:$J,6,FALSE))>0,VLOOKUP($B30,Catalogo!$A:$J,6,FALSE),IF(F30>0,F30/(1-Proyecto!$B$9),0)),0) | H30: =E30*F30 | I30: =E30*G30 | J30: =IFERROR(VLOOKUP($B30,Catalogo!$A:$J,9,FALSE),"") | K30: =IF(I30>0,(I30-H30)/I30,"") | L30: Ejecutiva de cada oficina administrativa.
A31: 5. Sillas y complementos | B31: SIL-INT | C31: =IFERROR(VLOOKUP($B31,Catalogo!$A:$J,2,FALSE),"CODIGO NO ENCONTRADO") | D31: =IFERROR(VLOOKUP($B31,Catalogo!$A:$J,4,FALSE),"") | E31: 6 | F31: =IFERROR(N(VLOOKUP($B31,Catalogo!$A:$J,5,FALSE)),0) | G31: =IFERROR(IF(N(VLOOKUP($B31,Catalogo!$A:$J,6,FALSE))>0,VLOOKUP($B31,Catalogo!$A:$J,6,FALSE),IF(F31>0,F31/(1-Proyecto!$B$9),0)),0) | H31: =E31*F31 | I31: =E31*G31 | J31: =IFERROR(VLOOKUP($B31,Catalogo!$A:$J,9,FALSE),"") | K31: =IF(I31>0,(I31-H31)/I31,"") | L31: 2 por oficina admin + 2 gerencia. Precio pendiente.
A32: 5. Sillas y complementos | B32: SIL-JUN | C32: =IFERROR(VLOOKUP($B32,Catalogo!$A:$J,2,FALSE),"CODIGO NO ENCONTRADO") | D32: =IFERROR(VLOOKUP($B32,Catalogo!$A:$J,4,FALSE),"") | E32: 6 | F32: =IFERROR(N(VLOOKUP($B32,Catalogo!$A:$J,5,FALSE)),0) | G32: =IFERROR(IF(N(VLOOKUP($B32,Catalogo!$A:$J,6,FALSE))>0,VLOOKUP($B32,Catalogo!$A:$J,6,FALSE),IF(F32>0,F32/(1-Proyecto!$B$9),0)),0) | H32: =E32*F32 | I32: =E32*G32 | J32: =IFERROR(VLOOKUP($B32,Catalogo!$A:$J,9,FALSE),"") | K32: =IF(I32>0,(I32-H32)/I32,"")
A33: 5. Sillas y complementos | B33: SIL-ISL | C33: =IFERROR(VLOOKUP($B33,Catalogo!$A:$J,2,FALSE),"CODIGO NO ENCONTRADO") | D33: =IFERROR(VLOOKUP($B33,Catalogo!$A:$J,4,FALSE),"") | E33: 6 | F33: =IFERROR(N(VLOOKUP($B33,Catalogo!$A:$J,5,FALSE)),0) | G33: =IFERROR(IF(N(VLOOKUP($B33,Catalogo!$A:$J,6,FALSE))>0,VLOOKUP($B33,Catalogo!$A:$J,6,FALSE),IF(F33>0,F33/(1-Proyecto!$B$9),0)),0) | H33: =E33*F33 | I33: =E33*G33 | J33: =IFERROR(VLOOKUP($B33,Catalogo!$A:$J,9,FALSE),"") | K33: =IF(I33>0,(I33-H33)/I33,"")
A34: 5. Sillas y complementos | B34: SOFA-2P | C34: =IFERROR(VLOOKUP($B34,Catalogo!$A:$J,2,FALSE),"CODIGO NO ENCONTRADO") | D34: =IFERROR(VLOOKUP($B34,Catalogo!$A:$J,4,FALSE),"") | E34: 1 | F34: =IFERROR(N(VLOOKUP($B34,Catalogo!$A:$J,5,FALSE)),0) | G34: =IFERROR(IF(N(VLOOKUP($B34,Catalogo!$A:$J,6,FALSE))>0,VLOOKUP($B34,Catalogo!$A:$J,6,FALSE),IF(F34>0,F34/(1-Proyecto!$B$9),0)),0) | H34: =E34*F34 | I34: =E34*G34 | J34: =IFERROR(VLOOKUP($B34,Catalogo!$A:$J,9,FALSE),"") | K34: =IF(I34>0,(I34-H34)/I34,"") | L34: Gerencia.
A35: 5. Sillas y complementos | B35: MESA-PEQ | C35: =IFERROR(VLOOKUP($B35,Catalogo!$A:$J,2,FALSE),"CODIGO NO ENCONTRADO") | D35: =IFERROR(VLOOKUP($B35,Catalogo!$A:$J,4,FALSE),"") | E35: 1 | F35: =IFERROR(N(VLOOKUP($B35,Catalogo!$A:$J,5,FALSE)),0) | G35: =IFERROR(IF(N(VLOOKUP($B35,Catalogo!$A:$J,6,FALSE))>0,VLOOKUP($B35,Catalogo!$A:$J,6,FALSE),IF(F35>0,F35/(1-Proyecto!$B$9),0)),0) | H35: =E35*F35 | I35: =E35*G35 | J35: =IFERROR(VLOOKUP($B35,Catalogo!$A:$J,9,FALSE),"") | K35: =IF(I35>0,(I35-H35)/I35,"") | L35: Gerencia.

Sheet Catalogo
A1: Codigo (ref. interna Odoo) | B1: Nombre | C1: Categoria | D1: UdM | E1: Costo | F1: Precio venta (si ya definido) | G1: Proveedor | H1: Fecha precio | I1: Estado precio | J1: Notas
A2: VID-SER-10 | B2: Vidrio templado 10 mm con serigrafia/pelicula (incluye vidrio) | C2: Vidrio | D2: m2 | E2: 345000 | I2: Referencia | J2: Dato del cliente: 'puede tener un costo de $345.000'. Confirmar.
A3: VID-TEM-10 | B3: Vidrio templado 10 mm transparente | C3: Vidrio | D3: m2 | E3: 150000 | I3: Confirmado | J3: Costo del cliente; sin boquetes, orificios ni herrajes.
A4: MO-VID-INST | B4: Instalacion de vidrio (subcontratista) | C4: Mano de obra | D4: m2 | E4: 80000 | G4: Subcontratista | I4: Confirmado | J4: Dato del cliente. Transporte y andamio no aplican.
A5: BOQ-VID | B5: Boquete en vidrio | C5: Vidrio | D5: und | E5: 15000 | I5: Referencia | J5: Aprox. segun cliente.
A6: ORI-VID | B6: Orificio en vidrio | C6: Vidrio | D6: und | E6: 4000 | I6: Confirmado
A7: BOQ-GRM | B7: Boquete para groom (mesa de juntas) | C7: Mobiliario | D7: und | E7: 15000 | I7: Referencia | J7: Se usa el precio de boquete como referencia.
A8: PER-L1-AL | B8: Perfil angulo L 1x1" aluminio mate | C8: Perfileria | D8: ml | I8: Pendiente | J8: Sin precio: no se pudo consultar mercado desde este entorno.
A9: SIL-EST | B9: Silicona de sellado de vidrio | C9: Insumos | D9: ml | I9: Pendiente
A10: PTA-MARCO-AL | B10: Marco de aluminio para hoja de puerta | C10: Puertas | D10: ml | I10: Pendiente
A11: PTA-CORR | B11: Sistema corredizo para puerta (riel y rodamientos) | C11: Herrajes | D11: juego | I11: Pendiente
A12: PTA-BIS | B12: Bisagra para puerta batiente | C12: Herrajes | D12: und | I12: Pendiente
A13: PTA-MAN | B13: Manija de puerta | C13: Herrajes | D13: und | I13: Pendiente
A14: PTA-TOPE | B14: Tope de puerta | C14: Herrajes | D14: und | I14: Pendiente
A15: PTA-CHAPA-PL | B15: Chapa cerradura pico de loro | C15: Herrajes | D15: und | I15: Pendiente
A16: PTA-PAS | B16: Pasador de puerta | C16: Herrajes | D16: und | I16: Pendiente
A17: TAB-15-215x244 | B17: Tablero 15 mm 2.15 x 2.44 m (Madecentro) | C17: Tableros | D17: hoja | E17: 450000 | G17: Madecentro | I17: Confirmado | J17: Dato del cliente.
A18: CANTO-3CM | B18: Canto rigido 3 cm instalado | C18: Tableros | D18: ml | E18: 9500 | I18: Confirmado | J18: Dato del cliente.
A19: ARCH-2X1 | B19: Archivador 2x1 mini | C19: Mobiliario | D19: und | I19: Pendiente
A20: TUB-2X2-C18 | B20: Tubo cuadrado 2x2" calibre 18 (barra 6 m) | C20: Estructura | D20: barra | I20: Pendiente | J20: Sin precio de mercado.
A21: PINT-ELEC | B21: Pintura electrostatica estructuras | C21: Estructura | D21: m2 | I21: Pendiente
A22: CAN-ELEC-ISLA | B22: Canaletas electricas y cableado estructurado isla | C22: Electrico | D22: global | I22: Pendiente
A23: SIL-GER | B23: Silla presidencial gerencia | C23: Sillas | D23: und | E23: 550000 | F23: 700000 | I23: Confirmado
A24: SIL-ADM | B24: Silla ejecutiva administrativa | C24: Sillas | D24: und | E24: 330000 | F24: 490000 | I24: Confirmado
A25: SIL-INT | B25: Silla interlocutora | C25: Sillas | D25: und | I25: Pendiente | J25: Costo y precio no dados.
A26: SIL-JUN | B26: Silla giratoria sala de juntas | C26: Sillas | D26: und | E26: 320000 | F26: 480000 | I26: Confirmado
A27: SIL-ISL | B27: Silla ejecutiva isla | C27: Sillas | D27: und | E27: 280000 | F27: 390000 | I27: Confirmado
A28: SOFA-2P | B28: Sofa 2 puestos gerencia | C28: Mobiliario | D28: und | E28: 700000 | F28: 1250000 | I28: Confirmado
A29: MESA-PEQ | B29: Mesa pequena gerencia | C29: Mobiliario | D29: und | E29: 200000 | F29: 290000 | I29: Confirmado

Sheet Opciones
A1: OPCIONES Y ALTERNATIVAS
A2: Complete los precios en amarillo para comparar.
A4: Opcion de vidrio | B4: Area (m2) | C4: Costo por m2 | D4: Costo total | E4: Venta total (margen objetivo)
A5: A. Serigrafia / pelicula negra y blanca (incluye vidrio) | B5: =Calculo_Vidrio!H13 | C5: 345000 | D5: =B5*N(C5) | E5: =D5/(1-Proyecto!$B$9)
A6: B. Pelicula matizada (precio por m2 pendiente) | B6: =Calculo_Vidrio!H13 | D6: =B6*N(C6) | E6: =D6/(1-Proyecto!$B$9)
A7: C. Opacado electronico (precio por m2 pendiente) | B7: =Calculo_Vidrio!H13 | D7: =B7*N(C7) | E7: =D7/(1-Proyecto!$B$9)
A9: Mas instalacion del vidrio (igual en todas las opciones): = | D9: =Calculo_Vidrio!H13*80000
A12: Tapas: madera vs vidrio | B12: Area 1 capa (m2) | C12: Costo por m2 / unidad | D12: Costo total
A13: Madera sandwich 15+15 (hojas + canto) | B13: =Cortes_Tablero!E19 | D13: =Cortes_Tablero!B22*450000+Cortes_Tablero!D19*9500
A14: Vidrio templado 10 mm (referencia $150.000/m2, sin pulido ni orificios) | B14: =Cortes_Tablero!E19 | C14: 150000 | D14: =B14*C14

Sheet Supuestos_Pendientes
A1: SUPUESTOS (revisar):
A2: 1. Longitudes de vidrio leidas del plano con las cotas visibles; 137 y 156 cm = ancho total del vano de cada puerta corrediza.
A3: 2. Altura de puertas 2.10 m; el resto hasta 2.42 m es vidrio fijo sobre la puerta.
A4: 3. Serigrafia/pelicula al 100% del vidrio (incluye hojas de puerta y vidrio sobre puertas) a $345.000/m2.
A5: 4. Perfil L 1x1: un angulo por cada cara del vidrio, en piso y techo.
A6: 5. Margen 45% = utilidad bruta sobre precio de venta (Venta = Costo / 0.55). Las sillas, sofa y mesa conservan su precio de venta.
A7: 6. Escritorio admin: 1.50x1.50 con 60 cm; gerencia: frente 1.70x0.75 + retorno 0.95x0.60; juntas 1.76x1.15; isla 6 tapas de 1.37x0.60.
A8: 7. Tapas en madera: 2 capas de 15 mm; canto rigido en todos los bordes de cada tapa; optimizacion con sierra de 4 mm y rotacion permitida.
A9: 8. Estructura metalica: perimetro bajo la tapa + 4 patas de 70 cm + travesanos; barras de 6 m.
A11: PRECIOS QUE FALTAN (no se pudieron consultar: este entorno no accede a Homecenter ni Mercado Libre):
A12: Perfil L 1x1 aluminio, silicona, marco de aluminio de puertas, sistema corredizo, bisagras, manijas, topes, chapa pico de loro, pasador,
A13: tubo cuadrado 2x2 cal. 18, pintura electrostatica, archivadores 2x1, canaletas/cableado de isla, sillas interlocutoras (6), pelicula matizada y opacado electronico.
... A21: f) Madera: tiene veta/dibujo que impida rotar piezas? Se arma la capa inferior con retales?

Sheet Import_Odoo
A1: Order Lines/Product | B1: Order Lines/Description | C1: Order Lines/Quantity | D1: Order Lines/Unit Price | E1: Order Lines/Unit of Measure | G1: Borrador: ajustar columnas al exportar una cotizacion de ejemplo de su Odoo. Filtrar filas vacias antes de importar.
A2: =IF(Presupuesto!B2="","",Presupuesto!B2) | B2: =IF(Presupuesto!B2="","",Presupuesto!C2) | C2: =IF(Presupuesto!B2="","",Presupuesto!E2) | D2: =IF(Presupuesto!B2="","",Presupuesto!G2) | E2: =IF(Presupuesto!B2="","",Presupuesto!D2)
A3: =IF(Presupuesto!B3="","",Presupuesto!B3) | B3: =IF(Presupuesto!B3="","",Presupuesto!C3) | C3: =IF(Presupuesto!B3="","",Presupuesto!E3) | D3: =IF(Presupuesto!B3="","",Presupuesto!G3) | E3: =IF(Presupuesto!B3="","",Presupuesto!D3)
A4: =IF(Presupuesto!B4="","",Presupuesto!B4) | B4: =IF(Presupuesto!B4="","",Presupuesto!C4) | C4: =IF(Presupuesto!B4="","",Presupuesto!E4) | D4: =IF(Presupuesto!B4="","",Presupuesto!G4) | E4: =IF(Presupuesto!B4="","",Presupuesto!D4)
A5: =IF(Presupuesto!B5="","",Presupuesto!B5) | B5: =IF(Presupuesto!B5="","",Presupuesto!C5) | C5: =IF(Presupuesto!B5="","",Presupuesto!E5) | D5: =IF(Presupuesto!B5="","",Presupuesto!G5) | E5: =IF(Presupuesto!B5="","",Presupuesto!D5)
A6: =IF(Presupuesto!B6="","",Presupuesto!B6) | B6: =IF(Presupuesto!B6="","",Presupuesto!C6) | C6: =IF(Presupuesto!B6="","",Presupuesto!E6) | D6: =IF(Presupuesto!B6="","",Presupuesto!G6) | E6: =IF(Presupuesto!B6="","",Presupuesto!D6)
A7: =IF(Presupuesto!B7="","",Presupuesto!B7) | B7: =IF(Presupuesto!B7="","",Presupuesto!C7) | C7: =IF(Presupuesto!B7="","",Presupuesto!E7) | D7: =IF(Presupuesto!B7="","",Presupuesto!G7) | E7: =IF(Presupuesto!B7="","",Presupuesto!D7)
A8: =IF(Presupuesto!B8="","",Presupuesto!B8) | B8: =IF(Presupuesto!B8="","",Presupuesto!C8) | C8: =IF(Presupuesto!B8="","",Presupuesto!E8) | D8: =IF(Presupuesto!B8="","",Presupuesto!G8) | E8: =IF(Presupuesto!B8="","",Presupuesto!D8)
A9: =IF(Presupuesto!B9="","",Presupuesto!B9) | B9: =IF(Presupuesto!B9="","",Presupuesto!C9) | C9: =IF(Presupuesto!B9="","",Presupuesto!E9) | D9: =IF(Presupuesto!B9="","",Presupuesto!G9) | E9: =IF(Presupuesto!B9="","",Presupuesto!D9)
A10: =IF(Presupuesto!B10="","",Presupuesto!B10) | B10: =IF(Presupuesto!B10="","",Presupuesto!C10) | C10: =IF(Presupuesto!B10="","",Presupuesto!E10) | D10: =IF(Presupuesto!B10="","",Presupuesto!G10) | E10: =IF(Presupuesto!B10="","",Presupuesto!D10)
A11: =IF(Presupuesto!B11="","",Presupuesto!B11) | B11: =IF(Presupuesto!B11="","",Presupuesto!C11) | C11: =IF(Presupuesto!B11="","",Presupuesto!E11) | D11: =IF(Presupuesto!B11="","",Presupuesto!G11) | E11: =IF(Presupuesto!B11="","",Presupuesto!D11)
A12: =IF(Presupuesto!B12="","",Presupuesto!B12) | B12: =IF(Presupuesto!B12="","",Presupuesto!C12) | C12: =IF(Presupuesto!B12="","",Presupuesto!E12) | D12: =IF(Presupuesto!B12="","",Presupuesto!G12) | E12: =IF(Presupuesto!B12="","",Presupuesto!D12)
A13: =IF(Presupuesto!B13="","",Presupuesto!B13) | B13: =IF(Presupuesto!B13="","",Presupuesto!C13) | C13: =IF(Presupuesto!B13="","",Presupuesto!E13) | D13: =IF(Presupuesto!B13="","",Presupuesto!G13) | E13: =IF(Presupuesto!B13="","",Presupuesto!D13)
... A35: =IF(Presupuesto!B35="","",Presupuesto!B35) | B35: =IF(Presupuesto!B35="","",Presupuesto!C35) | C35: =IF(Presupuesto!B35="","",Presupuesto!E35) | D35: =IF(Presupuesto!B35="","",Presupuesto!G35) | E35: =IF(Presupuesto!B35="","",Presupuesto!D35)
